<annotation>
	<folder>smallerset</folder>
	<filename>kframe203.jpg</filename>
	<path>C:\Users\ASingh\PycharmProjects\createframes2\smallerset\kframe203.jpg</path>
	<source>
		<database>Unknown</database>
	</source>
	<size>
		<width>638</width>
		<height>360</height>
		<depth>3</depth>
	</size>
	<segmented>0</segmented>
	<object>
		<name>ball</name>
		<pose>Unspecified</pose>
		<truncated>0</truncated>
		<difficult>0</difficult>
		<bndbox>
			<xmin>298</xmin>
			<ymin>193</ymin>
			<xmax>419</xmax>
			<ymax>315</ymax>
		</bndbox>
	</object>
</annotation>
